deepuq/.DS_Store
deepuq/__init__.py
deepuq/analyze/__init__.py
deepuq/analyze/analyze.py
deepuq/data/__init__.py
deepuq/data/data.py
deepuq/models/__init__.py
deepuq/models/models.py
deepuq/scripts/DeepEnsemble.py
deepuq/scripts/DeepEvidentialRegression.py
deepuq/scripts/DeepUQResources/DER_test.yml
deepuq/scripts/DeepUQResources/results/DE_noise_low_beta_0.5_nmodel_0_epoch_1.pt
deepuq/scripts/DeepUQResources/results/DE_noise_low_beta_0.5_nmodel_1_epoch_1.pt
deepuq/scripts/DeepUQResources/temp/temp_config_DE.yml
deepuq/scripts/DeepUQResources/temp/temp_config_DER.yml
deepuq/scripts/DeepUQResources/temp/temp_config_analysis.yml
deepuq/scripts/LossFunctions.py
deepuq/scripts/__init__.py
deepuq/scripts/__version__.py
deepuq/scripts/old_analysis/Aleatoric.py
deepuq/scripts/old_analysis/AleatoricNHidden.py
deepuq/scripts/old_analysis/Aleatoric_and_inits.py
deepuq/scripts/old_analysis/AleatoricandEpistemic.py
deepuq/scripts/old_analysis/Epistemic.py
deepuq/scripts/old_analysis/ParityPlotTest.py
deepuq/scripts/potentially_delete/2dDeepEvidentialRegression.py
deepuq/scripts/potentially_delete/ExperimentalExpectedSigmaTest.py
deepuq/scripts/potentially_delete/ParitySigma.py
deepuq/train/__init__.py
deepuq/train/train.py
deepuq/utils/__init__.py
deepuq/utils/config.py
deepuq/utils/defaults.py
deepuq-0.1.6.dist-info/LICENSE.txt
deepuq-0.1.6.dist-info/METADATA
deepuq-0.1.6.dist-info/WHEEL
deepuq-0.1.6.dist-info/entry_points.txt
deepuq-0.1.6.dist-info/RECORD
