Metadata-Version: 2.1
Name: deepuq
Version: 0.1.6
Summary: a package for investigating and comparing the predictive uncertainties from deep learning models
License: MIT
Author: beckynevin
Author-email: beckynevin@gmail.com
Requires-Python: >=3.10,<3.11
Classifier: License :: OSI Approved :: MIT License
Classifier: Programming Language :: Python :: 3
Classifier: Programming Language :: Python :: 3.10
Requires-Dist: deepbench (>=0.2.3,<0.3.0)
Requires-Dist: h5py (>=3.10.0,<4.0.0)
Requires-Dist: jupyter (>=1.0.0,<2.0.0)
Requires-Dist: matplotlib (>=3.7.1,<4.0.0)
Requires-Dist: scikit-learn (>=1.3.0,<2.0.0)
Requires-Dist: seaborn (>=0.12.2,<0.13.0)
Requires-Dist: torch (>=2.0.1,<3.0.0)
